pybudgetplot/__about__.py
pybudgetplot/__init__.py
pybudgetplot/cli/__init__.py
pybudgetplot/datamodel/__init__.py
pybudgetplot/datamodel/budget.py
pybudgetplot/datamodel/event.py
pybudgetplot/datamodel/period.py
pybudgetplot/utils/__init__.py
pybudgetplot/utils/file_util.py
pybudgetplot/utils/log_util.py
pybudgetplot/utils/plot_util.py
pybudgetplot/utils/xlsx_util.py
pybudgetplot-3.1.1.dist-info/METADATA
pybudgetplot-3.1.1.dist-info/WHEEL
pybudgetplot-3.1.1.dist-info/entry_points.txt
pybudgetplot-3.1.1.dist-info/licenses/LICENSE.txt
pybudgetplot-3.1.1.dist-info/RECORD
