Metadata-Version: 2.1
Name: pybudgetplot
Version: 3.1.1
Summary: CLI app to read and plot budget definition to multiple formats.
Project-URL: Documentation, https://github.com/Hrissimir/PyBudgetPlot#readme
Project-URL: Issues, https://github.com/Hrissimir/PyBudgetPlot/issues
Project-URL: Source, https://github.com/Hrissimir/PyBudgetPlot
Author-email: Hrissimir <hrisimir.dakov@gmail.com>
Maintainer-email: Hrissimir <hrisimir.dakov@gmail.com>
License-File: LICENSE.txt
Classifier: Development Status :: 5 - Production/Stable
Classifier: Environment :: Console
Classifier: Intended Audience :: Education
Classifier: Intended Audience :: End Users/Desktop
Classifier: Intended Audience :: Financial and Insurance Industry
Classifier: Intended Audience :: Information Technology
Classifier: License :: OSI Approved :: MIT License
Classifier: Operating System :: OS Independent
Classifier: Programming Language :: Python
Classifier: Programming Language :: Python :: 3.7
Classifier: Programming Language :: Python :: 3.8
Classifier: Programming Language :: Python :: 3.9
Classifier: Programming Language :: Python :: 3.10
Classifier: Programming Language :: Python :: 3.11
Classifier: Programming Language :: Python :: Implementation :: CPython
Classifier: Programming Language :: Python :: Implementation :: PyPy
Classifier: Topic :: Office/Business :: Financial
Classifier: Topic :: Office/Business :: Financial :: Accounting
Classifier: Topic :: Office/Business :: Financial :: Spreadsheet
Classifier: Topic :: Utilities
Requires-Python: >=3.7
Requires-Dist: click>=8.1.3
Requires-Dist: matplotlib>=3.5.3
Requires-Dist: numpy>=1.21.6
Requires-Dist: pandas>=1.3.5
Requires-Dist: parsedatetime>=2.6
Requires-Dist: python-dateutil>=2.8.2
Requires-Dist: pytz>=2022.6
Requires-Dist: pyyaml>=6.0
Requires-Dist: recurrent>=0.4.1
Requires-Dist: tabulate>=0.9.0
Requires-Dist: xlsxwriter>=3.0.3
